{
  "date": "2026-04-11",
  "summary": "週末停火談判緊盯，本週美股三大指數全線大漲3-5%",
  "us": {
    "dow": "-0.56%",
    "nasdaq": "+0.35%",
    "sp500": "-0.11%"
  },
  "tw": {
    "change": "+1.60%",
    "points": "+557",
    "note": "台股週五（4/10）延續強勢，加權指數以35,417.83點作收，周漲幅顯著。外資本週維持買超，AI與半導體族群為資金集中地，台積電Q1營收年增35%大幅超預期、股價突破2,000元大關帶動整體市場信心。週末市場聚焦美伊和談結果，若談判順利將為下週開盤注入信心；反之則需防範油價反彈帶來的賣壓。",
    "sectors": ["台積電/半導體", "AI供應鏈", "光通訊", "電動車"]
  },
  "events": [
    {
      "icon": "🕊️",
      "title": "美伊代表赴巴基斯坦和談",
      "detail": "伊朗代表團在伊斯蘭堡會見巴基斯坦總理，若美方接受伊朗先決條件，正式談判將於當日下午啟動。美伊停火協議脆弱，週末談判結果將左右下週油價與市場情緒。",
      "meta": "09:00 · 金十數據 / Yahoo Finance"
    },
    {
      "icon": "🇹🇼",
      "title": "台積電Q1營收大增35%",
      "detail": "台積電公布第一季總營收達1兆1,341億新台幣，年增35%，大幅超越華爾街預期，主要受惠於AI應用需求持續旺盛，AI晶片訂單能見度高至明年。",
      "meta": "08:00 · CNBC / Yahoo Finance"
    },
    {
      "icon": "📉",
      "title": "美消費信心跌至歷史新低",
      "detail": "密西根大學4月消費者信心指數降至47.6，創歷史最低紀錄，一年期通膨預期大幅跳升。民眾對通膨前景與就業市場憂慮加深，聯準會降息路徑更加複雜。",
      "meta": "22:00 · CNBC / Bloomberg"
    },
    {
      "icon": "⛽",
      "title": "3月CPI能源漲幅帶動指數攀升",
      "detail": "美國3月CPI年增符合預期，但能源價格大漲推升整體通膨，全國汽油均價突破每加侖4美元。能源通膨壓力持續，聯準會降息時程恐再推遲至2026年底。",
      "meta": "21:30 · Reuters / Yahoo Finance"
    },
    {
      "icon": "🚗",
      "title": "中國新能源車2030滲透率逾70%",
      "detail": "智能電動汽車高層論壇宣示「十五五」建成汽車強國目標，預計2030年新能源車國內市場滲透率超過70%，相關供應鏈個股受消息刺激走強。",
      "meta": "10:00 · 金十數據"
    }
  ],
  "risks": [
    "美伊停火脆弱，談判破裂將導致油價急彈、全球市場回吐",
    "消費信心指數創歷史新低（47.6），美國景氣衰退憂慮升溫",
    "CPI持續偏高加上能源漲價，聯準會降息預期遭壓後",
    "台股35,000點上方獲利了結壓力，高檔震盪風險仍在"
  ],
  "tomorrow": [
    "週末美伊巴基斯坦和談進展，影響週一開盤油價與風險情緒",
    "台積電2,000元關卡能否守穩，外資下週動向為關鍵",
    "聯準會官員發言，留意對降息路徑的最新表態"
  ],
  "sources": ["Yahoo Finance", "CNBC", "鉅亨網", "金十數據", "Reuters"],
  "generated": "2026-04-11 11:45"
}
